BGColorGenerator/__init__.py
BGColorGenerator/utils/__init__.py
BGColorGenerator/utils/best_model.keras
BGColorGenerator/utils/colorgenerator.py
BGColorGenerator/utils/visualization.py
BGColorGenerator/utils/__pycache__/colorgenerator.cpython-311.pyc
BGColorGenerator/utils/__pycache__/visualization.cpython-311.pyc
BGColorGenerator-2.1.3.dist-info/METADATA
BGColorGenerator-2.1.3.dist-info/WHEEL
BGColorGenerator-2.1.3.dist-info/top_level.txt
BGColorGenerator-2.1.3.dist-info/RECORD
