Metadata-Version: 2.1
Name: BGColorGenerator
Version: 2.1.3
Summary: A package for predicting the background color based on text color using a trained neural network.
Home-page: https://github.com/joaquinsc999/BGColorGenerator
Author: Joaquín Francisco Solórzano Corea
Author-email: joaquinscorea@gmail.com
Classifier: Programming Language :: Python :: 3.7
Classifier: License :: OSI Approved :: MIT License
Classifier: Operating System :: OS Independent
Requires-Python: >=3.7
Requires-Dist: tensorflow>=2.0.0
Requires-Dist: matplotlib
Requires-Dist: pandas
Requires-Dist: numpy
